{
    "$schema": "https://vega.github.io/schema/vega-lite/v5.json",
    "description": "A simple bar chart with embedded data.",
    "title": {
        "text": "Adjusted Closing Price GBP/USD",
        "subtitle":" Adjusted Closing price is after all apllicable splits and dividends (Source: Yahoo Finance)",
        "subtitleFontStyle":"italic",
        "subtitleFontSize":10,
        "anchor": "start",
        "color": "black"},
    "data": {
      "values": [{"Date": "2021-10-21", "Open": 1.382361, "High": 1.383399, "Low": 1.378721, "Close": 1.3823, "Adj Close": 1.3823, "Volume": 0}, {"Date": "2021-10-22", "Open": 1.37912, "High": 1.381425, "Low": 1.374306, "Close": 1.37912, "Adj Close": 1.37912, "Volume": 0}, {"Date": "2021-10-25", "Open": 1.376652, "High": 1.379177, "Low": 1.374344, "Close": 1.376273, "Adj Close": 1.376273, "Volume": 0}, {"Date": "2021-10-26", "Open": 1.376614, "High": 1.382954, "Low": 1.375819, "Close": 1.376444, "Adj Close": 1.376444, "Volume": 0}, {"Date": "2021-10-27", "Open": 1.376842, "High": 1.378037, "Low": 1.371084, "Close": 1.376614, "Adj Close": 1.376614, "Volume": 0}, {"Date": "2021-10-28", "Open": 1.373249, "High": 1.381521, "Low": 1.372307, "Close": 1.373287, "Adj Close": 1.373287, "Volume": 0}, {"Date": "2021-10-29", "Open": 1.380072, "High": 1.380453, "Low": 1.368176, "Close": 1.380072, "Adj Close": 1.380072, "Volume": 0}, {"Date": "2021-11-01", "Open": 1.368644, "High": 1.369244, "Low": 1.364238, "Close": 1.368326, "Adj Close": 1.368326, "Volume": 0}, {"Date": "2021-11-02", "Open": 1.365934, "High": 1.366718, "Low": 1.361081, "Close": 1.365542, "Adj Close": 1.365542, "Volume": 0}, {"Date": "2021-11-03", "Open": 1.361748, "High": 1.366456, "Low": 1.361137, "Close": 1.361739, "Adj Close": 1.361739, "Volume": 0}, {"Date": "2021-11-04", "Open": 1.369357, "High": 1.369469, "Low": 1.34732, "Close": 1.369488, "Adj Close": 1.369488, "Volume": 0}, {"Date": "2021-11-05", "Open": 1.35095, "High": 1.350986, "Low": 1.342588, "Close": 1.35086, "Adj Close": 1.35086, "Volume": 0}, {"Date": "2021-11-08", "Open": 1.348963, "High": 1.357976, "Low": 1.345189, "Close": 1.349127, "Adj Close": 1.349127, "Volume": 0}, {"Date": "2021-11-09", "Open": 1.356374, "High": 1.360544, "Low": 1.352631, "Close": 1.356451, "Adj Close": 1.356451, "Volume": 0}, {"Date": "2021-11-10", "Open": 1.356098, "High": 1.356668, "Low": 1.346838, "Close": 1.356, "Adj Close": 1.356, "Volume": 0}, {"Date": "2021-11-11", "Open": 1.341274, "High": 1.343274, "Low": 1.337023, "Close": 1.341274, "Adj Close": 1.341274, "Volume": 0}, {"Date": "2021-11-12", "Open": 1.33672, "High": 1.342282, "Low": 1.335399, "Close": 1.336648, "Adj Close": 1.336648, "Volume": 0}, {"Date": "2021-11-15", "Open": 1.341688, "High": 1.344954, "Low": 1.340393, "Close": 1.341706, "Adj Close": 1.341706, "Volume": 0}, {"Date": "2021-11-16", "Open": 1.341094, "High": 1.347346, "Low": 1.341094, "Close": 1.340842, "Adj Close": 1.340842, "Volume": 0}, {"Date": "2021-11-17", "Open": 1.342426, "High": 1.349018, "Low": 1.340267, "Close": 1.342462, "Adj Close": 1.342462, "Volume": 0}, {"Date": "2021-11-18", "Open": 1.348963, "High": 1.35139, "Low": 1.34654, "Close": 1.349164, "Adj Close": 1.349164, "Volume": 0}, {"Date": "2021-11-19", "Open": 1.349837, "High": 1.350986, "Low": 1.340842, "Close": 1.349965, "Adj Close": 1.349965, "Volume": 0}, {"Date": "2021-11-22", "Open": 1.34336, "High": 1.34499, "Low": 1.339226, "Close": 1.343454, "Adj Close": 1.343454, "Volume": 0}, {"Date": "2021-11-23", "Open": 1.339764, "High": 1.340842, "Low": 1.334419, "Close": 1.339764, "Adj Close": 1.339764, "Volume": 0}, {"Date": "2021-11-24", "Open": 1.337578, "High": 1.338975, "Low": 1.332481, "Close": 1.337596, "Adj Close": 1.337596, "Volume": 0}, {"Date": "2021-11-25", "Open": 1.333102, "High": 1.335301, "Low": 1.330654, "Close": 1.333067, "Adj Close": 1.333067, "Volume": 0}, {"Date": "2021-11-26", "Open": 1.331345, "High": 1.334846, "Low": 1.328057, "Close": 1.331416, "Adj Close": 1.331416, "Volume": 0}, {"Date": "2021-11-29", "Open": 1.333956, "High": 1.336309, "Low": 1.329027, "Close": 1.334098, "Adj Close": 1.334098, "Volume": 0}, {"Date": "2021-11-30", "Open": 1.331664, "High": 1.336934, "Low": 1.32062, "Close": 1.331505, "Adj Close": 1.331505, "Volume": 0}, {"Date": "2021-12-01", "Open": 1.329593, "High": 1.335113, "Low": 1.327721, "Close": 1.329593, "Adj Close": 1.329593, "Volume": 0}, {"Date": "2021-12-02", "Open": 1.327933, "High": 1.333262, "Low": 1.327246, "Close": 1.328, "Adj Close": 1.328, "Volume": 0}, {"Date": "2021-12-03", "Open": 1.33007, "High": 1.330814, "Low": 1.321144, "Close": 1.329999, "Adj Close": 1.329999, "Volume": 0}, {"Date": "2021-12-06", "Open": 1.323294, "High": 1.328551, "Low": 1.322384, "Close": 1.323732, "Adj Close": 1.323732, "Volume": 0}, {"Date": "2021-12-07", "Open": 1.326418, "High": 1.328974, "Low": 1.321056, "Close": 1.326436, "Adj Close": 1.326436, "Volume": 0}, {"Date": "2021-12-08", "Open": 1.324854, "High": 1.32626, "Low": 1.317471, "Close": 1.324609, "Adj Close": 1.324609, "Volume": 0}, {"Date": "2021-12-09", "Open": 1.321004, "High": 1.321702, "Low": 1.317627, "Close": 1.321004, "Adj Close": 1.321004, "Volume": 0}, {"Date": "2021-12-10", "Open": 1.322489, "High": 1.327105, "Low": 1.319087, "Close": 1.322401, "Adj Close": 1.322401, "Volume": 0}, {"Date": "2021-12-13", "Open": 1.325803, "High": 1.326876, "Low": 1.322244, "Close": 1.325715, "Adj Close": 1.325715, "Volume": 0}, {"Date": "2021-12-14", "Open": 1.321336, "High": 1.325557, "Low": 1.319087, "Close": 1.321353, "Adj Close": 1.321353, "Volume": 0}, {"Date": "2021-12-15", "Open": 1.323136, "High": 1.328286, "Low": 1.320812, "Close": 1.323051, "Adj Close": 1.323051, "Volume": 0}, {"Date": "2021-12-16", "Open": 1.326401, "High": 1.337327, "Low": 1.32431, "Close": 1.326313, "Adj Close": 1.326313, "Volume": 0}, {"Date": "2021-12-17", "Open": 1.332427, "High": 1.334045, "Low": 1.325768, "Close": 1.332374, "Adj Close": 1.332374, "Volume": 0}, {"Date": "2021-12-20", "Open": 1.322996, "High": 1.324345, "Low": 1.317402, "Close": 1.322944, "Adj Close": 1.322944, "Volume": 0}, {"Date": "2021-12-21", "Open": 1.320987, "High": 1.326119, "Low": 1.319975, "Close": 1.321, "Adj Close": 1.321, "Volume": 0}, {"Date": "2021-12-22", "Open": 1.326999, "High": 1.336237, "Low": 1.324135, "Close": 1.326964, "Adj Close": 1.326964, "Volume": 0}, {"Date": "2021-12-23", "Open": 1.335203, "High": 1.343725, "Low": 1.334508, "Close": 1.335203, "Adj Close": 1.335203, "Volume": 0}, {"Date": "2021-12-24", "Open": 1.340914, "High": 1.34257, "Low": 1.339405, "Close": 1.340662, "Adj Close": 1.340662, "Volume": 0}, {"Date": "2021-12-27", "Open": 1.34052, "High": 1.34407, "Low": 1.339226, "Close": 1.34043, "Adj Close": 1.34043, "Volume": 0}, {"Date": "2021-12-28", "Open": 1.344447, "High": 1.346257, "Low": 1.341832, "Close": 1.344267, "Adj Close": 1.344267, "Volume": 0}, {"Date": "2021-12-29", "Open": 1.3434, "High": 1.349928, "Low": 1.340914, "Close": 1.343328, "Adj Close": 1.343328, "Volume": 0}, {"Date": "2021-12-30", "Open": 1.349764, "High": 1.352155, "Low": 1.345533, "Close": 1.349879, "Adj Close": 1.349879, "Volume": 0}, {"Date": "2021-12-31", "Open": 1.349892, "High": 1.354848, "Low": 1.346747, "Close": 1.349837, "Adj Close": 1.349837, "Volume": 0}, {"Date": "2022-01-03", "Open": 1.352228, "High": 1.35318, "Low": 1.343274, "Close": 1.352228, "Adj Close": 1.352228, "Volume": 0}, {"Date": "2022-01-04", "Open": 1.348279, "High": 1.355675, "Low": 1.346076, "Close": 1.348327, "Adj Close": 1.348327, "Volume": 0}, {"Date": "2022-01-05", "Open": 1.353052, "High": 1.357331, "Low": 1.352265, "Close": 1.353143, "Adj Close": 1.353143, "Volume": 0}, {"Date": "2022-01-06", "Open": 1.355546, "High": 1.355748, "Low": 1.349109, "Close": 1.355565, "Adj Close": 1.355565, "Volume": 0}, {"Date": "2022-01-07", "Open": 1.3534, "High": 1.358345, "Low": 1.352942, "Close": 1.353363, "Adj Close": 1.353363, "Volume": 0}, {"Date": "2022-01-10", "Open": 1.359083, "High": 1.360193, "Low": 1.353418, "Close": 1.359231, "Adj Close": 1.359231, "Volume": 0}, {"Date": "2022-01-11", "Open": 1.35817, "High": 1.362416, "Low": 1.356282, "Close": 1.358031, "Adj Close": 1.358031, "Volume": 0}, {"Date": "2022-01-12", "Open": 1.363401, "High": 1.369938, "Low": 1.362212, "Close": 1.363327, "Adj Close": 1.363327, "Volume": 0}, {"Date": "2022-01-13", "Open": 1.370689, "High": 1.374949, "Low": 1.370558, "Close": 1.370999, "Adj Close": 1.370999, "Volume": 0}, {"Date": "2022-01-14", "Open": 1.371291, "High": 1.374193, "Low": 1.36677, "Close": 1.371366, "Adj Close": 1.371366, "Volume": 0}, {"Date": "2022-01-17", "Open": 1.367353, "High": 1.368899, "Low": 1.363866, "Close": 1.367353, "Adj Close": 1.367353, "Volume": 0}, {"Date": "2022-01-18", "Open": 1.3648, "High": 1.36612, "Low": 1.357626, "Close": 1.3648, "Adj Close": 1.3648, "Volume": 0}, {"Date": "2022-01-19", "Open": 1.360082, "High": 1.364815, "Low": 1.358936, "Close": 1.360026, "Adj Close": 1.360026, "Volume": 0}, {"Date": "2022-01-20", "Open": 1.360952, "High": 1.366158, "Low": 1.360156, "Close": 1.360859, "Adj Close": 1.360859, "Volume": 0}, {"Date": "2022-01-21", "Open": 1.360026, "High": 1.360359, "Low": 1.354757, "Close": 1.359767, "Adj Close": 1.359767, "Volume": 0}, {"Date": "2022-01-24", "Open": 1.355491, "High": 1.356668, "Low": 1.344303, "Close": 1.355583, "Adj Close": 1.355583, "Volume": 0}, {"Date": "2022-01-25", "Open": 1.348981, "High": 1.350056, "Low": 1.343707, "Close": 1.348927, "Adj Close": 1.348927, "Volume": 0}, {"Date": "2022-01-26", "Open": 1.351041, "High": 1.352448, "Low": 1.349418, "Close": 1.351078, "Adj Close": 1.351078, "Volume": 0}, {"Date": "2022-01-27", "Open": 1.346783, "High": 1.346783, "Low": 1.336059, "Close": 1.346801, "Adj Close": 1.346801, "Volume": 0}, {"Date": "2022-01-28", "Open": 1.338849, "High": 1.343201, "Low": 1.336559, "Close": 1.338832, "Adj Close": 1.338832, "Volume": 0}, {"Date": "2022-01-31", "Open": 1.340213, "High": 1.345424, "Low": 1.339531, "Close": 1.340339, "Adj Close": 1.340339, "Volume": 0}, {"Date": "2022-02-01", "Open": 1.344267, "High": 1.351406, "Low": 1.34358, "Close": 1.344538, "Adj Close": 1.344538, "Volume": 0}, {"Date": "2022-02-02", "Open": 1.352393, "High": 1.358493, "Low": 1.351717, "Close": 1.352539, "Adj Close": 1.352539, "Volume": 0}, {"Date": "2022-02-03", "Open": 1.356447, "High": 1.362546, "Low": 1.353913, "Close": 1.356502, "Adj Close": 1.356502, "Volume": 0}, {"Date": "2022-02-04", "Open": 1.359619, "High": 1.361656, "Low": 1.350804, "Close": 1.359841, "Adj Close": 1.359841, "Volume": 0}, {"Date": "2022-02-07", "Open": 1.353363, "High": 1.355032, "Low": 1.349182, "Close": 1.353345, "Adj Close": 1.353345, "Volume": 0}, {"Date": "2022-02-08", "Open": 1.35384, "High": 1.356668, "Low": 1.350986, "Close": 1.353781, "Adj Close": 1.353781, "Volume": 0}, {"Date": "2022-02-09", "Open": 1.354812, "High": 1.358825, "Low": 1.353821, "Close": 1.354757, "Adj Close": 1.354757, "Volume": 0}, {"Date": "2022-02-10", "Open": 1.3534, "High": 1.364331, "Low": 1.352539, "Close": 1.353327, "Adj Close": 1.353327, "Volume": 0}, {"Date": "2022-02-11", "Open": 1.354977, "High": 1.360878, "Low": 1.351534, "Close": 1.355179, "Adj Close": 1.355179, "Volume": 0}, {"Date": "2022-02-14", "Open": 1.357018, "High": 1.35722, "Low": 1.349582, "Close": 1.356963, "Adj Close": 1.356963, "Volume": 0}, {"Date": "2022-02-15", "Open": 1.353327, "High": 1.356686, "Low": 1.349018, "Close": 1.35329, "Adj Close": 1.35329, "Volume": 0}, {"Date": "2022-02-16", "Open": 1.354115, "High": 1.358991, "Low": 1.353913, "Close": 1.354115, "Adj Close": 1.354115, "Volume": 0}, {"Date": "2022-02-17", "Open": 1.358234, "High": 1.363643, "Low": 1.355803, "Close": 1.358493, "Adj Close": 1.358493, "Volume": 0}, {"Date": "2022-02-18", "Open": 1.361544, "High": 1.36407, "Low": 1.357442, "Close": 1.361878, "Adj Close": 1.361878, "Volume": 0}, {"Date": "2022-02-21", "Open": 1.359179, "High": 1.363829, "Low": 1.358714, "Close": 1.359342, "Adj Close": 1.359342, "Volume": 0}, {"Date": "2022-02-22", "Open": 1.359527, "High": 1.360544, "Low": 1.354005, "Close": 1.359601, "Adj Close": 1.359601, "Volume": 0}, {"Date": "2022-02-23", "Open": 1.359083, "High": 1.361953, "Low": 1.354922, "Close": 1.358936, "Adj Close": 1.358936, "Volume": 0}, {"Date": "2022-02-24", "Open": 1.354463, "High": 1.354738, "Low": 1.327598, "Close": 1.354573, "Adj Close": 1.354573, "Volume": 0}, {"Date": "2022-02-25", "Open": 1.33722, "High": 1.343905, "Low": 1.336898, "Close": 1.337327, "Adj Close": 1.337327, "Volume": 0}, {"Date": "2022-02-28", "Open": 1.337006, "High": 1.343111, "Low": 1.334258, "Close": 1.337327, "Adj Close": 1.337327, "Volume": 0}, {"Date": "2022-03-01", "Open": 1.342282, "High": 1.343725, "Low": 1.331203, "Close": 1.342282, "Adj Close": 1.342282, "Volume": 0}, {"Date": "2022-03-02", "Open": 1.333333, "High": 1.337095, "Low": 1.327404, "Close": 1.333511, "Adj Close": 1.333511, "Volume": 0}, {"Date": "2022-03-03", "Open": 1.339728, "High": 1.341796, "Low": 1.332037, "Close": 1.339692, "Adj Close": 1.339692, "Volume": 0}, {"Date": "2022-03-04", "Open": 1.335131, "High": 1.335131, "Low": 1.320533, "Close": 1.335096, "Adj Close": 1.335096, "Volume": 0}, {"Date": "2022-03-07", "Open": 1.321248, "High": 1.322594, "Low": 1.310393, "Close": 1.321248, "Adj Close": 1.321248, "Volume": 0}, {"Date": "2022-03-08", "Open": 1.311407, "High": 1.314285, "Low": 1.30837, "Close": 1.31123, "Adj Close": 1.31123, "Volume": 0}, {"Date": "2022-03-09", "Open": 1.310255, "High": 1.318235, "Low": 1.309929, "Close": 1.309929, "Adj Close": 1.309929, "Volume": 0}, {"Date": "2022-03-10", "Open": 1.318844, "High": 1.31947, "Low": 1.310736, "Close": 1.318565, "Adj Close": 1.318565, "Volume": 0}, {"Date": "2022-03-11", "Open": 1.310307, "High": 1.312491, "Low": 1.305244, "Close": 1.310324, "Adj Close": 1.310324, "Volume": 0}, {"Date": "2022-03-14", "Open": 1.304955, "High": 1.307873, "Low": 1.30105, "Close": 1.30503, "Adj Close": 1.30503, "Volume": 0}, {"Date": "2022-03-15", "Open": 1.301084, "High": 1.308866, "Low": 1.300136, "Close": 1.301185, "Adj Close": 1.301185, "Volume": 0}, {"Date": "2022-03-16", "Open": 1.3045, "High": 1.311441, "Low": 1.303662, "Close": 1.304649, "Adj Close": 1.304649, "Volume": 0}, {"Date": "2022-03-17", "Open": 1.314078, "High": 1.321109, "Low": 1.308952, "Close": 1.314112, "Adj Close": 1.314112, "Volume": 0}, {"Date": "2022-03-18", "Open": 1.316049, "High": 1.318166, "Low": 1.3112, "Close": 1.316041, "Adj Close": 1.316041, "Volume": 0}, {"Date": "2022-03-21", "Open": 1.316067, "High": 1.320987, "Low": 1.312836, "Close": 1.316084, "Adj Close": 1.316084, "Volume": 0}, {"Date": "2022-03-22", "Open": 1.316794, "High": 1.327246, "Low": 1.312095, "Close": 1.316829, "Adj Close": 1.316829, "Volume": 0}, {"Date": "2022-03-23", "Open": 1.326964, "High": 1.329893, "Low": 1.317627, "Close": 1.326647, "Adj Close": 1.326647, "Volume": 0}, {"Date": "2022-03-24", "Open": 1.320655, "High": 1.321475, "Low": 1.315789, "Close": 1.320603, "Adj Close": 1.320603, "Volume": 0}, {"Date": "2022-03-25", "Open": 1.319592, "High": 1.322559, "Low": 1.31617, "Close": 1.319575, "Adj Close": 1.319575, "Volume": 0}, {"Date": "2022-03-28", "Open": 1.317697, "High": 1.317888, "Low": 1.306865, "Close": 1.317627, "Adj Close": 1.317627, "Volume": 0}, {"Date": "2022-03-29", "Open": 1.309998, "High": 1.315928, "Low": 1.305227, "Close": 1.310358, "Adj Close": 1.310358, "Volume": 0}, {"Date": "2022-03-30", "Open": 1.309295, "High": 1.318061, "Low": 1.309158, "Close": 1.30938, "Adj Close": 1.30938, "Volume": 0}, {"Date": "2022-03-31", "Open": 1.313681, "High": 1.317089, "Low": 1.31096, "Close": 1.313888, "Adj Close": 1.313888, "Volume": 0}, {"Date": "2022-04-01", "Open": 1.314579, "High": 1.314613, "Low": 1.308866, "Close": 1.3147, "Adj Close": 1.3147, "Volume": 0}, {"Date": "2022-04-04", "Open": 1.310513, "High": 1.313629, "Low": 1.309518, "Close": 1.310376, "Adj Close": 1.310376, "Volume": 0}, {"Date": "2022-04-05", "Open": 1.311303, "High": 1.31669, "Low": 1.310049, "Close": 1.311458, "Adj Close": 1.311458, "Volume": 0}, {"Date": "2022-04-06", "Open": 1.307634, "High": 1.310685, "Low": 1.304665, "Close": 1.307737, "Adj Close": 1.307737, "Volume": 0}, {"Date": "2022-04-07", "Open": 1.307172, "High": 1.310668, "Low": 1.3055, "Close": 1.307207, "Adj Close": 1.307207, "Volume": 0}, {"Date": "2022-04-08", "Open": 1.306865, "High": 1.307873, "Low": 1.298482, "Close": 1.306933, "Adj Close": 1.306933, "Volume": 0}, {"Date": "2022-04-11", "Open": 1.302948, "High": 1.305756, "Low": 1.298988, "Close": 1.30322, "Adj Close": 1.30322, "Volume": 0}, {"Date": "2022-04-12", "Open": 1.302355, "High": 1.305364, "Low": 1.299697, "Close": 1.302423, "Adj Close": 1.302423, "Volume": 0}, {"Date": "2022-04-13", "Open": 1.300349, "High": 1.307155, "Low": 1.297438, "Close": 1.300255, "Adj Close": 1.300255, "Volume": 0}, {"Date": "2022-04-14", "Open": 1.312215, "High": 1.314752, "Low": 1.303815, "Close": 1.312026, "Adj Close": 1.312026, "Volume": 0}, {"Date": "2022-04-15", "Open": 1.306165, "High": 1.307668, "Low": 1.305279, "Close": 1.307002, "Adj Close": 1.307002, "Volume": 0}, {"Date": "2022-04-18", "Open": 1.305773, "High": 1.305773, "Low": 1.300796, "Close": 1.305756, "Adj Close": 1.305756, "Volume": 0}, {"Date": "2022-04-19", "Open": 1.300762, "High": 1.303985, "Low": 1.29833, "Close": 1.300982, "Adj Close": 1.300982, "Volume": 0}, {"Date": "2022-04-20", "Open": 1.301575, "High": 1.306677, "Low": 1.299798, "Close": 1.301372, "Adj Close": 1.301372, "Volume": 0}, {"Date": "2022-04-21", "Open": 1.306814, "High": 1.308832, "Low": 1.302423, "Close": 1.306882, "Adj Close": 1.306882, "Volume": 0}, {"Date": "2022-04-22", "Open": 1.302406, "High": 1.303373, "Low": 1.284076, "Close": 1.302626, "Adj Close": 1.302626, "Volume": 0}, {"Date": "2022-04-25", "Open": 1.282907, "High": 1.282972, "Low": 1.269906, "Close": 1.283088, "Adj Close": 1.283088, "Volume": 0}, {"Date": "2022-04-26", "Open": 1.273723, "High": 1.277237, "Low": 1.261304, "Close": 1.273999, "Adj Close": 1.273999, "Volume": 0}, {"Date": "2022-04-27", "Open": 1.258447, "High": 1.260081, "Low": 1.250391, "Close": 1.2584, "Adj Close": 1.2584, "Volume": 0}, {"Date": "2022-04-28", "Open": 1.253966, "High": 1.256676, "Low": 1.241403, "Close": 1.254186, "Adj Close": 1.254186, "Volume": 0}, {"Date": "2022-04-29", "Open": 1.246805, "High": 1.258352, "Low": 1.246727, "Close": 1.246385, "Adj Close": 1.246385, "Volume": 0}, {"Date": "2022-05-02", "Open": 1.257379, "High": 1.259636, "Low": 1.250531, "Close": 1.257387, "Adj Close": 1.257387, "Volume": 0}, {"Date": "2022-05-03", "Open": 1.250109, "High": 1.256644, "Low": 1.24938, "Close": 1.249828, "Adj Close": 1.249828, "Volume": 0}, {"Date": "2022-05-04", "Open": 1.249938, "High": 1.253761, "Low": 1.246743, "Close": 1.250041, "Adj Close": 1.250041, "Volume": 0}, {"Date": "2022-05-05", "Open": 1.261893, "High": 1.263169, "Low": 1.232757, "Close": 1.261814, "Adj Close": 1.261814, "Volume": 0}, {"Date": "2022-05-06", "Open": 1.236644, "High": 1.238022, "Low": 1.22777, "Close": 1.236415, "Adj Close": 1.236415, "Volume": 0}, {"Date": "2022-05-09", "Open": 1.232894, "High": 1.240495, "Low": 1.226212, "Close": 1.232666, "Adj Close": 1.232666, "Volume": 0}, {"Date": "2022-05-10", "Open": 1.233487, "High": 1.237471, "Low": 1.229377, "Close": 1.233882, "Adj Close": 1.233882, "Volume": 0}, {"Date": "2022-05-11", "Open": 1.230754, "High": 1.239803, "Low": 1.228199, "Close": 1.230921, "Adj Close": 1.230921, "Volume": 0}, {"Date": "2022-05-12", "Open": 1.223466, "High": 1.224815, "Low": 1.217137, "Close": 1.223421, "Adj Close": 1.223421, "Volume": 0}, {"Date": "2022-05-13", "Open": 1.220435, "High": 1.224515, "Low": 1.215717, "Close": 1.220614, "Adj Close": 1.220614, "Volume": 0}, {"Date": "2022-05-16", "Open": 1.226151, "High": 1.229725, "Low": 1.221896, "Close": 1.225851, "Adj Close": 1.225851, "Volume": 0}, {"Date": "2022-05-17", "Open": 1.232711, "High": 1.249812, "Low": 1.23221, "Close": 1.232483, "Adj Close": 1.232483, "Volume": 0}, {"Date": "2022-05-18", "Open": 1.249048, "High": 1.250062, "Low": 1.237425, "Close": 1.248439, "Adj Close": 1.248439, "Volume": 0}, {"Date": "2022-05-19", "Open": 1.234766, "High": 1.25227, "Low": 1.234065, "Close": 1.234583, "Adj Close": 1.234583, "Volume": 0}, {"Date": "2022-05-20", "Open": 1.246556, "High": 1.249875, "Low": 1.243967, "Close": 1.246215, "Adj Close": 1.246215, "Volume": 0}, {"Date": "2022-05-23", "Open": 1.250688, "High": 1.260112, "Low": 1.250125, "Close": 1.250406, "Adj Close": 1.250406, "Volume": 0}, {"Date": "2022-05-24", "Open": 1.256771, "High": 1.259684, "Low": 1.247272, "Close": 1.256755, "Adj Close": 1.256755, "Volume": 0}, {"Date": "2022-05-25", "Open": 1.254154, "High": 1.255792, "Low": 1.248424, "Close": 1.254296, "Adj Close": 1.254296, "Volume": 0}, {"Date": "2022-05-26", "Open": 1.258701, "High": 1.262116, "Low": 1.255304, "Close": 1.25861, "Adj Close": 1.25861, "Volume": 0}, {"Date": "2022-05-27", "Open": 1.261862, "High": 1.266624, "Low": 1.258717, "Close": 1.261734, "Adj Close": 1.261734, "Volume": 0}, {"Date": "2022-05-30", "Open": 1.262515, "High": 1.266031, "Low": 1.261766, "Close": 1.262834, "Adj Close": 1.262834, "Volume": 0}, {"Date": "2022-05-31", "Open": 1.264526, "High": 1.264846, "Low": 1.25625, "Close": 1.264702, "Adj Close": 1.264702, "Volume": 0}, {"Date": "2022-06-01", "Open": 1.26097, "High": 1.261686, "Low": 1.246013, "Close": 1.260891, "Adj Close": 1.260891, "Volume": 0}, {"Date": "2022-06-02", "Open": 1.248424, "High": 1.25696, "Low": 1.247038, "Close": 1.248315, "Adj Close": 1.248315, "Volume": 0}, {"Date": "2022-06-03", "Open": 1.257782, "High": 1.259002, "Low": 1.249453, "Close": 1.257925, "Adj Close": 1.257925, "Volume": 0}, {"Date": "2022-06-06", "Open": 1.248829, "High": 1.257703, "Low": 1.247988, "Close": 1.24923, "Adj Close": 1.24923, "Volume": 0}, {"Date": "2022-06-07", "Open": 1.252317, "High": 1.259446, "Low": 1.243441, "Close": 1.252348, "Adj Close": 1.252348, "Volume": 0}, {"Date": "2022-06-08", "Open": 1.258606, "High": 1.258986, "Low": 1.251502, "Close": 1.258732, "Adj Close": 1.258732, "Volume": 0}, {"Date": "2022-06-09", "Open": 1.254217, "High": 1.255398, "Low": 1.249297, "Close": 1.254029, "Adj Close": 1.254029, "Volume": 0}, {"Date": "2022-06-10", "Open": 1.249375, "High": 1.251815, "Low": 1.231557, "Close": 1.249297, "Adj Close": 1.249297, "Volume": 0}, {"Date": "2022-06-13", "Open": 1.227807, "High": 1.230012, "Low": 1.212768, "Close": 1.227491, "Adj Close": 1.227491, "Volume": 0}, {"Date": "2022-06-14", "Open": 1.214403, "High": 1.220271, "Low": 1.199256, "Close": 1.214477, "Adj Close": 1.214477, "Volume": 0}, {"Date": "2022-06-15", "Open": 1.201345, "High": 1.212533, "Low": 1.199213, "Close": 1.201259, "Adj Close": 1.201259, "Volume": 0}, {"Date": "2022-06-16", "Open": 1.218145, "High": 1.234492, "Low": 1.205037, "Close": 1.217434, "Adj Close": 1.217434, "Volume": 0}, {"Date": "2022-06-17", "Open": 1.235025, "High": 1.235025, "Low": 1.217404, "Close": 1.235483, "Adj Close": 1.235483, "Volume": 0}, {"Date": "2022-06-20", "Open": 1.222823, "High": 1.227777, "Low": 1.220063, "Close": 1.222823, "Adj Close": 1.222823, "Volume": 0}, {"Date": "2022-06-21", "Open": 1.22501, "High": 1.231922, "Low": 1.22492, "Close": 1.225175, "Adj Close": 1.225175, "Volume": 0}, {"Date": "2022-06-22", "Open": 1.226407, "High": 1.231467, "Low": 1.216856, "Close": 1.226663, "Adj Close": 1.226663, "Volume": 0}, {"Date": "2022-06-23", "Open": 1.225325, "High": 1.229468, "Low": 1.217182, "Close": 1.225085, "Adj Close": 1.225085, "Volume": 0}, {"Date": "2022-06-24", "Open": 1.226196, "High": 1.231679, "Low": 1.22435, "Close": 1.226076, "Adj Close": 1.226076, "Volume": 0}, {"Date": "2022-06-27", "Open": 1.228803, "High": 1.233076, "Low": 1.223975, "Close": 1.228245, "Adj Close": 1.228245, "Volume": 0}, {"Date": "2022-06-28", "Open": 1.226753, "High": 1.229105, "Low": 1.218769, "Close": 1.226738, "Adj Close": 1.226738, "Volume": 0}, {"Date": "2022-06-29", "Open": 1.218635, "High": 1.221225, "Low": 1.210683, "Close": 1.218977, "Adj Close": 1.218977, "Volume": 0}, {"Date": "2022-06-30", "Open": 1.213106, "High": 1.218621, "Low": 1.209438, "Close": 1.21318, "Adj Close": 1.21318, "Volume": 0}, {"Date": "2022-07-01", "Open": 1.215998, "High": 1.216205, "Low": 1.198064, "Close": 1.216086, "Adj Close": 1.216086, "Volume": 0}, {"Date": "2022-07-04", "Open": 1.21058, "High": 1.216515, "Low": 1.208634, "Close": 1.210273, "Adj Close": 1.210273, "Volume": 0}, {"Date": "2022-07-05", "Open": 1.211402, "High": 1.212606, "Low": 1.190051, "Close": 1.211446, "Adj Close": 1.211446, "Volume": 0}, {"Date": "2022-07-06", "Open": 1.194957, "High": 1.198638, "Low": 1.187761, "Close": 1.194914, "Adj Close": 1.194914, "Volume": 0}, {"Date": "2022-07-07", "Open": 1.191895, "High": 1.202183, "Low": 1.191001, "Close": 1.192321, "Adj Close": 1.192321, "Volume": 0}, {"Date": "2022-07-08", "Open": 1.203196, "High": 1.205531, "Low": 1.192194, "Close": 1.202805, "Adj Close": 1.202805, "Volume": 0}, {"Date": "2022-07-11", "Open": 1.201779, "High": 1.201995, "Low": 1.186944, "Close": 1.201663, "Adj Close": 1.201663, "Volume": 0}, {"Date": "2022-07-12", "Open": 1.189994, "High": 1.191214, "Low": 1.181126, "Close": 1.190094, "Adj Close": 1.190094, "Volume": 0}, {"Date": "2022-07-13", "Open": 1.188269, "High": 1.195943, "Low": 1.18353, "Close": 1.187775, "Adj Close": 1.187775, "Volume": 0}, {"Date": "2022-07-14", "Open": 1.186197, "High": 1.188411, "Low": 1.176318, "Close": 1.18638, "Adj Close": 1.18638, "Volume": 0}, {"Date": "2022-07-15", "Open": 1.183866, "High": 1.187366, "Low": 1.180596, "Close": 1.183964, "Adj Close": 1.183964, "Volume": 0}, {"Date": "2022-07-18", "Open": 1.188792, "High": 1.203022, "Low": 1.18755, "Close": 1.188834, "Adj Close": 1.188834, "Volume": 0}, {"Date": "2022-07-19", "Open": 1.195072, "High": 1.204282, "Low": 1.192933, "Close": 1.194829, "Adj Close": 1.194829, "Volume": 0}, {"Date": "2022-07-20", "Open": 1.200423, "High": 1.203659, "Low": 1.195829, "Close": 1.200351, "Adj Close": 1.200351, "Volume": 0}, {"Date": "2022-07-21", "Open": 1.196616, "High": 1.200235, "Low": 1.189301, "Close": 1.197175, "Adj Close": 1.197175, "Volume": 0}, {"Date": "2022-07-22", "Open": 1.199688, "High": 1.206418, "Low": 1.192023, "Close": 1.199616, "Adj Close": 1.199616, "Volume": 0}, {"Date": "2022-07-25", "Open": 1.198423, "High": 1.208313, "Low": 1.196215, "Close": 1.198696, "Adj Close": 1.198696, "Volume": 0}, {"Date": "2022-07-26", "Open": 1.205764, "High": 1.209219, "Low": 1.196544, "Close": 1.205516, "Adj Close": 1.205516, "Volume": 0}, {"Date": "2022-07-27", "Open": 1.203818, "High": 1.208664, "Low": 1.202227, "Close": 1.203688, "Adj Close": 1.203688, "Volume": 0}, {"Date": "2022-07-28", "Open": 1.216663, "High": 1.219051, "Low": 1.210449, "Close": 1.216308, "Adj Close": 1.216308, "Volume": 0}, {"Date": "2022-07-29", "Open": 1.217448, "High": 1.22426, "Low": 1.206709, "Close": 1.217345, "Adj Close": 1.217345, "Volume": 0}, {"Date": "2022-08-01", "Open": 1.216782, "High": 1.229196, "Low": 1.216486, "Close": 1.216737, "Adj Close": 1.216737, "Volume": 0}, {"Date": "2022-08-02", "Open": 1.225956, "High": 1.227838, "Low": 1.218175, "Close": 1.225415, "Adj Close": 1.225415, "Volume": 0}, {"Date": "2022-08-03", "Open": 1.214786, "High": 1.220733, "Low": 1.210156, "Close": 1.2143, "Adj Close": 1.2143, "Volume": 0}, {"Date": "2022-08-04", "Open": 1.213946, "High": 1.219512, "Low": 1.207175, "Close": 1.213828, "Adj Close": 1.213828, "Volume": 0}, {"Date": "2022-08-05", "Open": 1.215924, "High": 1.216752, "Low": 1.200769, "Close": 1.21585, "Adj Close": 1.21585, "Volume": 0}, {"Date": "2022-08-08", "Open": 1.206389, "High": 1.213519, "Low": 1.204863, "Close": 1.205953, "Adj Close": 1.205953, "Volume": 0}, {"Date": "2022-08-09", "Open": 1.208503, "High": 1.21293, "Low": 1.206826, "Close": 1.208474, "Adj Close": 1.208474, "Volume": 0}, {"Date": "2022-08-10", "Open": 1.207263, "High": 1.227446, "Low": 1.206724, "Close": 1.207423, "Adj Close": 1.207423, "Volume": 0}, {"Date": "2022-08-11", "Open": 1.221285, "High": 1.22489, "Low": 1.218294, "Close": 1.2213, "Adj Close": 1.2213, "Volume": 0}, {"Date": "2022-08-12", "Open": 1.219661, "High": 1.221001, "Low": 1.210361, "Close": 1.219616, "Adj Close": 1.219616, "Volume": 0}, {"Date": "2022-08-15", "Open": 1.212989, "High": 1.214772, "Low": 1.205124, "Close": 1.212797, "Adj Close": 1.212797, "Volume": 0}, {"Date": "2022-08-16", "Open": 1.20556, "High": 1.211637, "Low": 1.200942, "Close": 1.205691, "Adj Close": 1.205691, "Volume": 0}, {"Date": "2022-08-17", "Open": 1.209673, "High": 1.213813, "Low": 1.202993, "Close": 1.209819, "Adj Close": 1.209819, "Volume": 0}, {"Date": "2022-08-18", "Open": 1.204587, "High": 1.207817, "Low": 1.196888, "Close": 1.204515, "Adj Close": 1.204515, "Volume": 0}, {"Date": "2022-08-19", "Open": 1.193374, "High": 1.193374, "Low": 1.179329, "Close": 1.193275, "Adj Close": 1.193275, "Volume": 0}, {"Date": "2022-08-22", "Open": 1.181768, "High": 1.183852, "Low": 1.17426, "Close": 1.18181, "Adj Close": 1.18181, "Volume": 0}, {"Date": "2022-08-23", "Open": 1.176706, "High": 1.187324, "Low": 1.172003, "Close": 1.176651, "Adj Close": 1.176651, "Volume": 0}, {"Date": "2022-08-24", "Open": 1.183152, "High": 1.186535, "Low": 1.175876, "Close": 1.183278, "Adj Close": 1.183278, "Volume": 0}, {"Date": "2022-08-25", "Open": 1.179023, "High": 1.186296, "Low": 1.178592, "Close": 1.179176, "Adj Close": 1.179176, "Volume": 0}, {"Date": "2022-08-26", "Open": 1.182592, "High": 1.190009, "Low": 1.175309, "Close": 1.182401, "Adj Close": 1.182401, "Volume": 0}, {"Date": "2022-08-29", "Open": 1.16918, "High": 1.17426, "Low": 1.164958, "Close": 1.169454, "Adj Close": 1.169454, "Volume": 0}, {"Date": "2022-08-30", "Open": 1.172127, "High": 1.175807, "Low": 1.162304, "Close": 1.172251, "Adj Close": 1.172251, "Volume": 0}, {"Date": "2022-08-31", "Open": 1.166086, "High": 1.169454, "Low": 1.160025, "Close": 1.165977, "Adj Close": 1.165977, "Volume": 0}, {"Date": "2022-09-01", "Open": 1.159689, "High": 1.16171, "Low": 1.150324, "Close": 1.159851, "Adj Close": 1.159851, "Volume": 0}, {"Date": "2022-09-02", "Open": 1.154734, "High": 1.158856, "Low": 1.153136, "Close": 1.154894, "Adj Close": 1.154894, "Volume": 0}, {"Date": "2022-09-05", "Open": 1.147855, "High": 1.152074, "Low": 1.144518, "Close": 1.14746, "Adj Close": 1.14746, "Volume": 0}, {"Date": "2022-09-06", "Open": 1.156885, "High": 1.160766, "Low": 1.149624, "Close": 1.156644, "Adj Close": 1.156644, "Volume": 0}, {"Date": "2022-09-07", "Open": 1.151278, "High": 1.152366, "Low": 1.140953, "Close": 1.151185, "Adj Close": 1.151185, "Volume": 0}, {"Date": "2022-09-08", "Open": 1.152246, "High": 1.156016, "Low": 1.146158, "Close": 1.151981, "Adj Close": 1.151981, "Volume": 0}, {"Date": "2022-09-09", "Open": 1.152047, "High": 1.164863, "Low": 1.151662, "Close": 1.15216, "Adj Close": 1.15216, "Volume": 0}, {"Date": "2022-09-12", "Open": 1.161805, "High": 1.171125, "Low": 1.160174, "Close": 1.16194, "Adj Close": 1.16194, "Volume": 0}, {"Date": "2022-09-13", "Open": 1.168975, "High": 1.173764, "Low": 1.152034, "Close": 1.168975, "Adj Close": 1.168975, "Volume": 0}, {"Date": "2022-09-14", "Open": 1.150351, "High": 1.158937, "Low": 1.148079, "Close": 1.150616, "Adj Close": 1.150616, "Volume": 0}, {"Date": "2022-09-15", "Open": 1.154294, "High": 1.154868, "Low": 1.146986, "Close": 1.154494, "Adj Close": 1.154494, "Volume": 0}, {"Date": "2022-09-16", "Open": 1.145475, "High": 1.148066, "Low": 1.135267, "Close": 1.145265, "Adj Close": 1.145265, "Volume": 0}, {"Date": "2022-09-19", "Open": 1.143641, "High": 1.144165, "Low": 1.135576, "Close": 1.143314, "Adj Close": 1.143314, "Volume": 0}, {"Date": "2022-09-20", "Open": 1.144846, "High": 1.14604, "Low": 1.138395, "Close": 1.144322, "Adj Close": 1.144322, "Volume": 0}, {"Date": "2022-09-21", "Open": 1.138071, "High": 1.138563, "Low": 1.130621, "Close": 1.138058, "Adj Close": 1.138058, "Volume": 0}, {"Date": "2022-09-22", "Open": 1.125518, "High": 1.136286, "Low": 1.121315, "Close": 1.125594, "Adj Close": 1.125594, "Volume": 0}, {"Date": "2022-09-23", "Open": 1.126304, "High": 1.127345, "Low": 1.089859, "Close": 1.126418, "Adj Close": 1.126418, "Volume": 0}, {"Date": "2022-09-26", "Open": 1.079914, "High": 1.09156, "Low": 1.037904, "Close": 1.079739, "Adj Close": 1.079739, "Volume": 0}, {"Date": "2022-09-27", "Open": 1.077006, "High": 1.083541, "Low": 1.073849, "Close": 1.077284, "Adj Close": 1.077284, "Volume": 0}, {"Date": "2022-09-28", "Open": 1.072846, "High": 1.083964, "Low": 1.054163, "Close": 1.072754, "Adj Close": 1.072754, "Volume": 0}, {"Date": "2022-09-29", "Open": 1.083459, "High": 1.106562, "Low": 1.076449, "Close": 1.0836, "Adj Close": 1.0836, "Volume": 0}, {"Date": "2022-09-30", "Open": 1.116184, "High": 1.123394, "Low": 1.102682, "Close": 1.116944, "Adj Close": 1.116944, "Volume": 0}, {"Date": "2022-10-03", "Open": 1.113648, "High": 1.133234, "Low": 1.108795, "Close": 1.114057, "Adj Close": 1.114057, "Volume": 0}, {"Date": "2022-10-04", "Open": 1.133967, "High": 1.144597, "Low": 1.128222, "Close": 1.133414, "Adj Close": 1.133414, "Volume": 0}, {"Date": "2022-10-05", "Open": 1.145056, "High": 1.149491, "Low": 1.122776, "Close": 1.145134, "Adj Close": 1.145134, "Volume": 0}, {"Date": "2022-10-06", "Open": 1.135589, "High": 1.138343, "Low": 1.112038, "Close": 1.135538, "Adj Close": 1.135538, "Volume": 0}, {"Date": "2022-10-07", "Open": 1.11652, "High": 1.122372, "Low": 1.109201, "Close": 1.116208, "Adj Close": 1.116208, "Volume": 0}, {"Date": "2022-10-10", "Open": 1.107444, "High": 1.111086, "Low": 1.102354, "Close": 1.107273, "Adj Close": 1.107273, "Volume": 0}, {"Date": "2022-10-11", "Open": 1.107849, "High": 1.117131, "Low": 1.100183, "Close": 1.107641, "Adj Close": 1.107641, "Volume": 0}, {"Date": "2022-10-12", "Open": 1.09678, "High": 1.109866, "Low": 1.092645, "Close": 1.09678, "Adj Close": 1.09678, "Volume": 0}, {"Date": "2022-10-13", "Open": 1.109927, "High": 1.136196, "Low": 1.105828, "Close": 1.110556, "Adj Close": 1.110556, "Volume": 0}, {"Date": "2022-10-14", "Open": 1.130148, "High": 1.135873, "Low": 1.116196, "Close": 1.130391, "Adj Close": 1.130391, "Volume": 0}, {"Date": "2022-10-17", "Open": 1.123873, "High": 1.143864, "Low": 1.121705, "Close": 1.124417, "Adj Close": 1.124417, "Volume": 0}, {"Date": "2022-10-18", "Open": 1.135525, "High": 1.141201, "Low": 1.125809, "Close": 1.135396, "Adj Close": 1.135396, "Volume": 0}, {"Date": "2022-10-19", "Open": 1.133954, "High": 1.134984, "Low": 1.122246, "Close": 1.13443, "Adj Close": 1.13443, "Volume": 0}, {"Date": "2022-10-20", "Open": 1.120951, "High": 1.133324, "Low": 1.117368, "Close": 1.121101, "Adj Close": 1.121101, "Volume": 0}, {"Date": "2022-10-21", "Open": 1.123684, "High": 1.123924, "Low": 1.112496, "Close": 1.114181, "Adj Close": 1.114181, "Volume": 0}]
      },
    "mark": "line",
    "encoding": {
      "x": {"field": "Date","timeUnit":"yearmonth", "type": "temporal"},
      "y": {"field": "Adj Close", "type": "quantitative"}
    }
  }
  